modlee/__init__.py
modlee/api_config.py
modlee/client.py
modlee/config.py
modlee/converter.py
modlee/data_metafeatures.py
modlee/dataframes.py
modlee/model_metafeatures.py
modlee/model_text_converter.py
modlee/retriever.py
modlee/utils.py
modlee/model/__init__.py
modlee/model/callbacks.py
modlee/model/image_model.py
modlee/model/model.py
modlee/model/recommended_model.py
modlee/model/tabular_model.py
modlee/model/text_model.py
modlee/model/timeseries_model.py
modlee/model/trainer.py
modlee/recommender/__init__.py
modlee/recommender/image_recommender.py
modlee/recommender/recommender.py
modlee/recommender/tabular_recommender.py
modlee/recommender/text_recommender.py
modlee/recommender/timeseries_recommender.py
modlee-0.0.5.dist-info/METADATA
modlee-0.0.5.dist-info/WHEEL
modlee-0.0.5.dist-info/top_level.txt
modlee-0.0.5.dist-info/RECORD
