Metadata-Version: 2.2
Name: modlee
Version: 0.0.5
Summary: modlee package
Author-email: modlee <brad@modlee.ai>
License: 
Project-URL: Homepage, https://www.modlee.ai
Project-URL: Source, https://www.github.com/modlee-ai/modlee
Requires-Python: >=3.10
Requires-Dist: pytorch-lightning==2.4.0
Requires-Dist: lightning==2.3.3
Requires-Dist: mlflow==2.16.2
Requires-Dist: networkx==2.6.3
Requires-Dist: numpy==1.26.4
Requires-Dist: pydantic==2.8.2
Requires-Dist: setuptools>=68.0.0
Requires-Dist: torch==2.3.0
Requires-Dist: torchmetrics==1.4.2
Requires-Dist: torchvision==0.18.0
Requires-Dist: torchtext==0.18.0
Requires-Dist: torchaudio==2.3.0
Requires-Dist: portalocker==2.10.1
Requires-Dist: torchdata==0.8.0
Requires-Dist: spacy==3.7.6
Requires-Dist: onnx==1.16.2
Requires-Dist: torchsummary==1.5.1
Requires-Dist: modlee-onnx2torch==1.5.15
Requires-Dist: modlee-onnx_graphsurgeon==0.3.27
Requires-Dist: pymfe==0.4.3
Requires-Dist: scipy==1.12.0
Requires-Dist: pydot==2.0.0
Requires-Dist: transformers==4.41.0
Requires-Dist: wonderwords
Provides-Extra: testing
Requires-Dist: pytest==8.1.1; extra == "testing"
Provides-Extra: docs
Requires-Dist: nbsphinx; extra == "docs"
Requires-Dist: sphinx-rtd-theme; extra == "docs"
